{"projectedScores":{"week":"20","playerScore":[{"score":"","id":"0530"},{"score":"","id":"11682"},{"score":"","id":"12155"},{"score":"","id":"11675"},{"score":"","id":"12181"},{"score":"","id":"12389"},{"score":"","id":"11983"},{"score":"","id":"10651"},{"score":"","id":"12154"},{"score":"","id":"9718"},{"score":"","id":"10082"},{"score":"","id":"12374"},{"score":"","id":"10742"},{"score":"","id":"12159"},{"score":"","id":"11222"},{"score":"","id":"12073"},{"score":"","id":"11696"},{"score":"9.1","id":"9308"},{"score":"9.7","id":"11454"},{"score":"1.3","id":"8025"},{"score":"","id":"12192"},{"score":"","id":"11702"},{"score":"","id":"11901"},{"score":"","id":"11961"},{"score":"","id":"11784"},{"score":"","id":"10232"},{"score":"3.8","id":"12161"},{"score":"","id":"10998"},{"score":"","id":"11923"},{"score":"","id":"12403"},{"score":"","id":"10464"},{"score":"","id":"8510"},{"score":"","id":"11213"},{"score":"","id":"8350"},{"score":"","id":"9040"},{"score":"","id":"12359"},{"score":"","id":"10506"},{"score":"","id":"12399"},{"score":"","id":"11223"},{"score":"","id":"10922"},{"score":"","id":"10527"},{"score":"","id":"11174"},{"score":"","id":"10715"},{"score":"","id":"11614"},{"score":"1.0","id":"11151"},{"score":"","id":"11177"},{"score":"","id":"9189"},{"score":"","id":"9307"},{"score":"","id":"11962"},{"score":"","id":"9017"},{"score":"","id":"11992"},{"score":"","id":"0521"},{"score":"","id":"10973"},{"score":"","id":"11679"},{"score":"","id":"12213"},{"score":"","id":"10048"},{"score":"","id":"12195"},{"score":"","id":"11192"},{"score":"","id":"12461"},{"score":"","id":"11104"},{"score":"","id":"0506"},{"score":"","id":"11673"},{"score":"","id":"10737"},{"score":"","id":"9859"},{"score":"","id":"9044"},{"score":"","id":"11193"},{"score":"","id":"11948"},{"score":"","id":"12214"},{"score":"","id":"11895"},{"score":"","id":"0501"},{"score":"","id":"10719"},{"score":"","id":"12267"},{"score":"","id":"11867"},{"score":"","id":"9898"},{"score":"","id":"11834"},{"score":"","id":"11340"},{"score":"","id":"11408"},{"score":"4.4","id":"10932"},{"score":"","id":"6982"},{"score":"","id":"11397"},{"score":"","id":"11642"},{"score":"","id":"11125"},{"score":"","id":"11936"},{"score":"","id":"8667"},{"score":"","id":"11224"},{"score":"","id":"11646"},{"score":"","id":"10930"},{"score":"","id":"12328"},{"score":"","id":"10972"},{"score":"","id":"9817"},{"score":"","id":"8917"},{"score":"33.3","id":"5848"},{"score":"","id":"12110"},{"score":"","id":"12561"},{"score":"","id":"11170"},{"score":"","id":"10889"},{"score":"","id":"4925"},{"score":"","id":"12412"},{"score":"","id":"11640"},{"score":"","id":"12416"},{"score":"","id":"9467"},{"score":"","id":"10681"},{"score":"","id":"10551"},{"score":"7.1","id":"0511"},{"score":"","id":"9565"},{"score":"","id":"9988"},{"score":"","id":"10905"},{"score":"8.2","id":"11972"},{"score":"","id":"12370"},{"score":"","id":"12585"},{"score":"","id":"12174"},{"score":"","id":"9456"},{"score":"2.9","id":"11456"},{"score":"14.0","id":"11783"},{"score":"","id":"7150"},{"score":"","id":"11393"},{"score":"","id":"12386"},{"score":"","id":"11481"},{"score":"","id":"11121"},{"score":"","id":"7814"},{"score":"","id":"10338"},{"score":"","id":"12432"},{"score":"","id":"0507"},{"score":"","id":"10732"},{"score":"","id":"9823"},{"score":"","id":"11688"},{"score":"","id":"6789"},{"score":"","id":"0525"},{"score":"","id":"10862"},{"score":"","id":"11182"},{"score":"","id":"11928"},{"score":"","id":"12325"},{"score":"","id":"11705"},{"score":"","id":"8685"},{"score":"","id":"8243"},{"score":"","id":"11406"},{"score":"","id":"11932"},{"score":"","id":"12464"},{"score":"","id":"10967"},{"score":"","id":"10978"},{"score":"1.6","id":"9050"},{"score":"","id":"10352"},{"score":"","id":"11857"},{"score":"","id":"7837"},{"score":"","id":"12149"},{"score":"6.7","id":"0519"},{"score":"","id":"11652"},{"score":"","id":"9052"},{"score":"","id":"9299"},{"score":"","id":"11644"},{"score":"","id":"10940"},{"score":"","id":"12394"},{"score":"","id":"12102"},{"score":"","id":"9480"},{"score":"","id":"8042"},{"score":"10.7","id":"11960"},{"score":"","id":"8838"},{"score":"","id":"11007"},{"score":"5.0","id":"8735"},{"score":"","id":"0514"},{"score":"","id":"9054"},{"score":"","id":"10747"},{"score":"","id":"0512"},{"score":"","id":"12385"},{"score":"","id":"9818"},{"score":"","id":"10409"},{"score":"","id":"12337"},{"score":"","id":"8290"},{"score":"","id":"12039"},{"score":"","id":"10552"},{"score":"","id":"12178"},{"score":"","id":"12158"},{"score":"","id":"10308"},{"score":"","id":"11911"},{"score":"","id":"9454"},{"score":"","id":"11754"},{"score":"","id":"11524"},{"score":"","id":"12152"},{"score":"","id":"9396"},{"score":"","id":"12421"},{"score":"","id":"8493"},{"score":"","id":"0502"},{"score":"","id":"12257"},{"score":"","id":"9950"},{"score":"","id":"9474"},{"score":"","id":"11674"},{"score":"","id":"11909"},{"score":"","id":"12175"},{"score":"","id":"9964"},{"score":"8.0","id":"7498"},{"score":"","id":"10700"},{"score":"","id":"0516"},{"score":"","id":"11426"},{"score":"","id":"12420"},{"score":"","id":"9427"},{"score":"","id":"8072"},{"score":"","id":"10866"},{"score":"","id":"12388"},{"score":"","id":"8742"},{"score":"","id":"12184"},{"score":"","id":"11668"},{"score":"","id":"10080"},{"score":"","id":"10139"},{"score":"","id":"6776"},{"score":"","id":"11432"},{"score":"","id":"12124"},{"score":"","id":"8252"},{"score":"","id":"10313"},{"score":"","id":"9706"},{"score":"","id":"11420"},{"score":"","id":"12203"},{"score":"6.8","id":"8339"},{"score":"","id":"11977"},{"score":"","id":"11001"},{"score":"","id":"12409"},{"score":"","id":"12265"},{"score":"","id":"11019"},{"score":"","id":"9058"},{"score":"","id":"12338"},{"score":"","id":"9205"},{"score":"","id":"11194"},{"score":"","id":"12164"},{"score":"","id":"12193"},{"score":"6.0","id":"8247"},{"score":"","id":"3494"},{"score":"","id":"12387"},{"score":"","id":"12364"},{"score":"","id":"9881"},{"score":"","id":"12116"},{"score":"","id":"12351"},{"score":"","id":"11101"},{"score":"","id":"11100"},{"score":"4.2","id":"9912"},{"score":"","id":"12186"},{"score":"","id":"9975"},{"score":"","id":"11933"},{"score":"","id":"11214"},{"score":"","id":"0503"},{"score":"","id":"11521"},{"score":"","id":"12188"},{"score":"","id":"11413"},{"score":"","id":"10310"},{"score":"","id":"9144"},{"score":"","id":"11516"},{"score":"","id":"10689"},{"score":"","id":"10015"},{"score":"","id":"10961"},{"score":"","id":"12448"},{"score":"","id":"12258"},{"score":"","id":"10356"},{"score":"","id":"9834"},{"score":"","id":"12541"},{"score":"","id":"12165"},{"score":"","id":"11157"},{"score":"","id":"0518"},{"score":"","id":"9931"},{"score":"","id":"11695"},{"score":"15.9","id":"9662"},{"score":"","id":"12599"},{"score":"","id":"12408"},{"score":"","id":"11250"},{"score":"7.2","id":"11175"},{"score":"","id":"11689"},{"score":"","id":"10838"},{"score":"","id":"11850"},{"score":"","id":"11247"},{"score":"","id":"11251"},{"score":"","id":"11671"},{"score":"","id":"11690"},{"score":"","id":"10860"},{"score":"","id":"12148"},{"score":"","id":"0526"},{"score":"","id":"11835"},{"score":"","id":"12396"},{"score":"","id":"8294"},{"score":"","id":"11243"},{"score":"","id":"4883"},{"score":"","id":"8532"},{"score":"5.0","id":"11337"},{"score":"","id":"9193"},{"score":"","id":"11698"},{"score":"","id":"9150"},{"score":"19.0","id":"7393"},{"score":"","id":"8062"},{"score":"","id":"9064"},{"score":"","id":"10743"},{"score":"","id":"1600"},{"score":"16.1","id":"10721"},{"score":"","id":"9254"},{"score":"","id":"10699"},{"score":"","id":"8851"},{"score":"","id":"10487"},{"score":"","id":"11587"},{"score":"","id":"9874"},{"score":"","id":"11195"},{"score":"","id":"9278"},{"score":"","id":"9122"},{"score":"","id":"9690"},{"score":"2.1","id":"11931"},{"score":"","id":"12294"},{"score":"","id":"12425"},{"score":"","id":"11660"},{"score":"","id":"9460"},{"score":"","id":"11866"},{"score":"","id":"11220"},{"score":"9.4","id":"12205"},{"score":"","id":"10262"},{"score":"","id":"11975"},{"score":"","id":"11661"},{"score":"","id":"11691"},{"score":"12.0","id":"9694"},{"score":"","id":"9250"},{"score":"","id":"12424"},{"score":"","id":"12199"},{"score":"1.0","id":"11760"},{"score":"","id":"11748"},{"score":"","id":"7236"},{"score":"","id":"12019"},{"score":"","id":"9880"},{"score":"","id":"0517"},{"score":"","id":"9625"},{"score":"","id":"11854"},{"score":"","id":"11180"},{"score":"","id":"11786"},{"score":"13.1","id":"8673"},{"score":"","id":"10736"},{"score":"","id":"11152"},{"score":"1.0","id":"11570"},{"score":"","id":"12194"},{"score":"","id":"11239"},{"score":"","id":"10960"},{"score":"","id":"12151"},{"score":"","id":"10414"},{"score":"","id":"7877"},{"score":"12.9","id":"8359"},{"score":"","id":"8153"},{"score":"","id":"8435"},{"score":"","id":"11256"},{"score":"","id":"9936"},{"score":"","id":"9925"},{"score":"","id":"6475"},{"score":"","id":"10813"},{"score":"","id":"12402"},{"score":"","id":"11812"},{"score":"","id":"10717"},{"score":"","id":"11332"},{"score":"","id":"11434"},{"score":"","id":"12146"},{"score":"","id":"10261"},{"score":"","id":"10744"},{"score":"2.3","id":"10432"},{"score":"","id":"12180"},{"score":"","id":"9347"},{"score":"","id":"12191"},{"score":"","id":"12183"},{"score":"","id":"9458"},{"score":"4.9","id":"9838"},{"score":"","id":"11655"},{"score":"","id":"10696"},{"score":"","id":"11399"},{"score":"","id":"11441"},{"score":"","id":"10975"},{"score":"16.9","id":"9902"},{"score":"","id":"6950"},{"score":"","id":"12150"},{"score":"","id":"8323"},{"score":"","id":"11122"},{"score":"","id":"12411"},{"score":"","id":"11215"},{"score":"","id":"11944"},{"score":"","id":"11967"},{"score":"","id":"10307"},{"score":"","id":"10877"},{"score":"","id":"9941"},{"score":"","id":"12185"},{"score":"","id":"11089"},{"score":"","id":"11235"},{"score":"","id":"12201"},{"score":"","id":"12190"},{"score":"","id":"12440"},{"score":"","id":"8910"},{"score":"","id":"11448"},{"score":"","id":"10530"},{"score":"","id":"10410"},{"score":"","id":"12105"},{"score":"","id":"11749"},{"score":"","id":"12404"},{"score":"","id":"12168"},{"score":"","id":"9360"},{"score":"","id":"9545"},{"score":"","id":"11022"},{"score":"","id":"9441"},{"score":"","id":"3445"},{"score":"","id":"9319"},{"score":"","id":"10601"},{"score":"","id":"12256"},{"score":"","id":"11839"},{"score":"","id":"12476"},{"score":"","id":"11981"},{"score":"","id":"10355"},{"score":"","id":"10913"},{"score":"","id":"10365"},{"score":"","id":"9073"},{"score":"","id":"12480"},{"score":"","id":"11968"},{"score":"","id":"10881"},{"score":"","id":"11755"},{"score":"","id":"8298"},{"score":"","id":"12208"},{"score":"","id":"11927"},{"score":"","id":"9452"},{"score":"","id":"9196"},{"score":"","id":"12200"},{"score":"","id":"11654"},{"score":"","id":"11529"},{"score":"","id":"12436"},{"score":"","id":"11435"},{"score":"","id":"7194"},{"score":"","id":"10800"},{"score":"","id":"12167"},{"score":"","id":"9272"},{"score":"10.6","id":"10812"},{"score":"","id":"10729"},{"score":"","id":"11865"},{"score":"","id":"10983"},{"score":"","id":"9990"},{"score":"","id":"10674"},{"score":"","id":"12499"},{"score":"","id":"8266"},{"score":"","id":"9946"},{"score":"","id":"11232"},{"score":"","id":"11387"},{"score":"","id":"11891"},{"score":"","id":"10333"},{"score":"","id":"9714"},{"score":"","id":"11684"},{"score":"","id":"11074"},{"score":"","id":"12505"},{"score":"","id":"12142"},{"score":"","id":"12170"},{"score":"","id":"12463"},{"score":"","id":"11212"},{"score":"","id":"10305"},{"score":"","id":"11925"},{"score":"","id":"11657"},{"score":"","id":"10567"},{"score":"","id":"10276"},{"score":"","id":"11957"},{"score":"","id":"12368"},{"score":"","id":"10077"},{"score":"","id":"9075"},{"score":"","id":"8934"},{"score":"5.4","id":"7414"},{"score":"","id":"8305"},{"score":"","id":"7873"},{"score":"","id":"12576"},{"score":"","id":"12046"},{"score":"","id":"0509"},{"score":"","id":"12211"},{"score":"","id":"10711"},{"score":"","id":"11190"},{"score":"","id":"5666"},{"score":"","id":"11870"},{"score":"","id":"10722"},{"score":"","id":"10803"},{"score":"","id":"12586"},{"score":"","id":"8293"},{"score":"","id":"9680"},{"score":"","id":"11699"},{"score":"","id":"10288"},{"score":"","id":"0505"},{"score":"","id":"6931"},{"score":"","id":"11989"},{"score":"","id":"8657"},{"score":"","id":"11409"},{"score":"","id":"9078"},{"score":"","id":"10953"},{"score":"13.8","id":"12171"},{"score":"","id":"9671"},{"score":"","id":"12157"},{"score":"","id":"12406"},{"score":"","id":"9207"},{"score":"","id":"12345"},{"score":"","id":"9269"},{"score":"","id":"11663"},{"score":"","id":"12400"},{"score":"","id":"11015"},{"score":"","id":"8772"},{"score":"","id":"8776"},{"score":"","id":"10271"},{"score":"","id":"11156"},{"score":"","id":"10738"},{"score":"","id":"12162"},{"score":"","id":"11921"},{"score":"","id":"11686"},{"score":"","id":"10368"},{"score":"","id":"8301"},{"score":"","id":"11664"},{"score":"","id":"11367"},{"score":"","id":"10297"},{"score":"","id":"9939"},{"score":"","id":"9979"},{"score":"","id":"11255"},{"score":"","id":"11076"},{"score":"","id":"10948"},{"score":"","id":"11244"},{"score":"","id":"12147"},{"score":"","id":"10318"},{"score":"","id":"10392"},{"score":"","id":"11219"},{"score":"","id":"12209"},{"score":"","id":"12577"},{"score":"","id":"12212"},{"score":"","id":"8590"},{"score":"","id":"12443"},{"score":"","id":"12596"},{"score":"10.7","id":"9843"},{"score":"","id":"11201"},{"score":"","id":"12417"},{"score":"","id":"11680"},{"score":"","id":"10992"},{"score":"","id":"12156"},{"score":"1.0","id":"11758"},{"score":"","id":"12587"},{"score":"","id":"12479"},{"score":"","id":"11672"},{"score":"","id":"12450"},{"score":"","id":"8709"},{"score":"","id":"11959"},{"score":"","id":"10281"},{"score":"","id":"12422"},{"score":"","id":"12371"},{"score":"","id":"10389"},{"score":"","id":"8269"},{"score":"","id":"10097"},{"score":"","id":"10705"},{"score":"","id":"11474"},{"score":"","id":"0522"},{"score":"","id":"10327"},{"score":"","id":"7052"},{"score":"","id":"10279"},{"score":"","id":"12187"},{"score":"","id":"10496"},{"score":"","id":"12410"},{"score":"","id":"10035"},{"score":"","id":"10695"},{"score":"","id":"12414"},{"score":"","id":"11704"},{"score":"","id":"11700"},{"score":"","id":"8670"},{"score":"","id":"9436"},{"score":"","id":"10511"},{"score":"","id":"12166"},{"score":"","id":"11666"},{"score":"","id":"10268"},{"score":"","id":"7391"},{"score":"18.0","id":"3291"},{"score":"","id":"9085"},{"score":"","id":"12145"},{"score":"","id":"12415"},{"score":"","id":"11154"},{"score":"","id":"11641"},{"score":"","id":"10009"},{"score":"","id":"12141"},{"score":"","id":"12475"},{"score":"","id":"8360"},{"score":"","id":"10709"},{"score":"5.4","id":"10835"},{"score":"","id":"12062"},{"score":"","id":"11650"},{"score":"","id":"9851"},{"score":"","id":"11752"},{"score":"","id":"11676"},{"score":"","id":"10903"},{"score":"","id":"12196"},{"score":"","id":"12260"},{"score":"","id":"11643"},{"score":"","id":"9856"},{"score":"","id":"6589"},{"score":"","id":"7496"},{"score":"","id":"9982"},{"score":"","id":"9899"},{"score":"","id":"9448"},{"score":"","id":"11257"},{"score":"","id":"9087"},{"score":"","id":"11465"},{"score":"","id":"11761"},{"score":"","id":"9892"},{"score":"12.4","id":"11947"},{"score":"","id":"8680"},{"score":"","id":"12465"},{"score":"","id":"11645"},{"score":"","id":"11179"},{"score":"","id":"11879"},{"score":"","id":"10437"},{"score":"","id":"7842"},{"score":"","id":"11086"},{"score":"","id":"10708"},{"score":"","id":"9611"},{"score":"","id":"8683"},{"score":"","id":"9924"},{"score":"","id":"11343"},{"score":"","id":"11677"},{"score":"","id":"12261"},{"score":"","id":"10388"},{"score":"","id":"10701"},{"score":"","id":"8178"},{"score":"","id":"10088"},{"score":"","id":"8944"},{"score":"","id":"9437"},{"score":"","id":"10517"},{"score":"","id":"9221"},{"score":"","id":"10870"},{"score":"","id":"11899"},{"score":"","id":"3309"},{"score":"","id":"4907"},{"score":"","id":"12447"},{"score":"","id":"9719"},{"score":"","id":"12331"},{"score":"","id":"9560"},{"score":"","id":"12367"},{"score":"","id":"12466"},{"score":"","id":"11648"},{"score":"","id":"10302"},{"score":"","id":"11390"},{"score":"","id":"11971"},{"score":"","id":"9632"},{"score":"","id":"12437"},{"score":"","id":"11155"},{"score":"","id":"11669"},{"score":"","id":"10072"},{"score":"2.6","id":"12319"},{"score":"","id":"9118"},{"score":"28.3","id":"10273"},{"score":"","id":"9450"},{"score":"1.4","id":"11703"},{"score":"","id":"4397"},{"score":"5.3","id":"9783"},{"score":"","id":"11798"},{"score":"","id":"12198"},{"score":"","id":"8144"},{"score":"","id":"7859"},{"score":"","id":"12467"},{"score":"","id":"12207"},{"score":"","id":"12330"},{"score":"","id":"12418"},{"score":"","id":"9641"},{"score":"","id":"9700"},{"score":"","id":"10985"},{"score":"","id":"11941"},{"score":"15.2","id":"8687"},{"score":"","id":"9972"},{"score":"","id":"7957"},{"score":"","id":"7918"},{"score":"","id":"7239"},{"score":"11.1","id":"10702"},{"score":"","id":"8549"},{"score":"","id":"10741"},{"score":"","id":"0523"},{"score":"25.6","id":"6929"},{"score":"","id":"8875"},{"score":"","id":"10113"},{"score":"7.3","id":"0527"},{"score":"","id":"12433"},{"score":"","id":"12176"},{"score":"","id":"10109"},{"score":"","id":"11966"},{"score":"","id":"9615"},{"score":"5.7","id":"0504"},{"score":"","id":"11225"},{"score":"","id":"11218"},{"score":"","id":"11976"},{"score":"","id":"10394"},{"score":"","id":"10123"},{"score":"","id":"10718"},{"score":"","id":"9616"},{"score":"","id":"12100"},{"score":"","id":"12197"},{"score":"","id":"11964"},{"score":"","id":"8658"},{"score":"","id":"9444"},{"score":"","id":"10311"},{"score":"","id":"12144"},{"score":"","id":"9638"},{"score":"","id":"12453"},{"score":"","id":"10713"},{"score":"","id":"9933"},{"score":"","id":"10710"},{"score":"","id":"10296"},{"score":"","id":"10730"},{"score":"","id":"10369"},{"score":"","id":"11843"},{"score":"","id":"8930"},{"score":"","id":"11851"},{"score":"","id":"12309"},{"score":"","id":"10500"},{"score":"","id":"9960"},{"score":"","id":"10735"},{"score":"","id":"0513"},{"score":"","id":"10929"},{"score":"","id":"0528"},{"score":"","id":"11200"},{"score":"","id":"10725"},{"score":"","id":"0531"},{"score":"","id":"12169"},{"score":"","id":"11942"},{"score":"","id":"11665"},{"score":"","id":"0520"},{"score":"","id":"9802"},{"score":"","id":"11248"},{"score":"","id":"11875"},{"score":"","id":"11162"},{"score":"","id":"11900"},{"score":"","id":"11540"},{"score":"","id":"9094"},{"score":"","id":"10924"},{"score":"","id":"11681"},{"score":"","id":"11477"},{"score":"","id":"10706"},{"score":"","id":"11188"},{"score":"","id":"10334"},{"score":"","id":"12353"},{"score":"","id":"11258"},{"score":"","id":"7394"},{"score":"","id":"9921"},{"score":"","id":"12471"},{"score":"","id":"10837"},{"score":"","id":"10412"},{"score":"","id":"11678"},{"score":"","id":"11210"},{"score":"","id":"10933"},{"score":"","id":"12163"},{"score":"","id":"11466"},{"score":"","id":"7836"},{"score":"","id":"10300"},{"score":"","id":"11785"},{"score":"","id":"10830"},{"score":"","id":"7401"},{"score":"","id":"11226"},{"score":"","id":"11475"},{"score":"","id":"12172"},{"score":"","id":"7260"},{"score":"","id":"8832"},{"score":"","id":"10797"},{"score":"","id":"12038"},{"score":"","id":"9120"},{"score":"","id":"10411"},{"score":"","id":"10312"},{"score":"","id":"12401"},{"score":"","id":"9099"},{"score":"","id":"0529"},{"score":"","id":"10360"},{"score":"","id":"9429"},{"score":"","id":"11233"},{"score":"18.5","id":"9918"},{"score":"","id":"11653"},{"score":"","id":"11945"},{"score":"","id":"10723"},{"score":"","id":"10497"},{"score":"","id":"12350"},{"score":"","id":"11683"},{"score":"","id":"11649"},{"score":"","id":"12405"},{"score":"","id":"7480"},{"score":"","id":"12407"},{"score":"","id":"7527"},{"score":"","id":"0515"},{"score":"","id":"11651"},{"score":"","id":"11697"},{"score":"","id":"11897"},{"score":"","id":"11237"},{"score":"","id":"10378"},{"score":"","id":"12397"},{"score":"","id":"10362"},{"score":"","id":"12381"},{"score":"","id":"11494"},{"score":"","id":"12138"},{"score":"","id":"9124"},{"score":"","id":"12143"},{"score":"","id":"11656"},{"score":"","id":"11249"},{"score":"","id":"9200"},{"score":"","id":"12259"},{"score":"","id":"11864"},{"score":"","id":"12204"},{"score":"","id":"7813"},{"score":"","id":"7883"},{"score":"","id":"10203"},{"score":"","id":"10067"},{"score":"","id":"8344"},{"score":"","id":"12182"},{"score":"","id":"12413"},{"score":"","id":"11150"},{"score":"","id":"12131"},{"score":"","id":"12571"},{"score":"","id":"10398"},{"score":"","id":"11221"},{"score":"","id":"12444"},{"score":"","id":"4974"},{"score":"","id":"10289"},{"score":"","id":"11951"},{"score":"","id":"8736"},{"score":"","id":"11889"},{"score":"","id":"12339"},{"score":"","id":"9822"},{"score":"","id":"7942"},{"score":"","id":"8641"},{"score":"","id":"11189"},{"score":"","id":"9431"},{"score":"1.2","id":"8712"},{"score":"","id":"9987"},{"score":"","id":"0510"},{"score":"","id":"12363"},{"score":"","id":"9145"},{"score":"","id":"11083"},{"score":"10.2","id":"9101"},{"score":"","id":"11227"},{"score":"","id":"10354"},{"score":"","id":"11245"},{"score":"","id":"10955"},{"score":"","id":"11687"},{"score":"","id":"10885"},{"score":"","id":"12179"},{"score":"","id":"11384"},{"score":"","id":"9686"},{"score":"","id":"11259"},{"score":"","id":"8160"},{"score":"","id":"9601"},{"score":"","id":"11628"},{"score":"","id":"12378"},{"score":"","id":"11904"},{"score":"","id":"11081"},{"score":"","id":"11809"},{"score":"","id":"11617"},{"score":"","id":"9176"},{"score":"","id":"10697"},{"score":"","id":"10515"},{"score":"","id":"10935"},{"score":"","id":"9907"},{"score":"","id":"9524"},{"score":"","id":"9831"},{"score":"","id":"12398"},{"score":"","id":"10442"},{"score":"2.3","id":"11176"},{"score":"","id":"10413"},{"score":"","id":"9862"},{"score":"","id":"12347"},{"score":"","id":"0532"},{"score":"","id":"11938"},{"score":"","id":"11006"},{"score":"","id":"10299"},{"score":"","id":"11659"},{"score":"19.7","id":"9884"},{"score":"","id":"10372"},{"score":"","id":"11647"},{"score":"","id":"8931"},{"score":"","id":"11440"},{"score":"","id":"11186"},{"score":"","id":"10956"},{"score":"","id":"12572"},{"score":"2.0","id":"11937"},{"score":"","id":"10852"},{"score":"","id":"11943"},{"score":"","id":"0508"},{"score":"","id":"10301"},{"score":"","id":"11252"},{"score":"8.2","id":"9315"},{"score":"","id":"10498"},{"score":"","id":"10731"},{"score":"","id":"12009"},{"score":"","id":"10976"},{"score":"","id":"11431"},{"score":"","id":"10241"},{"score":"","id":"10714"},{"score":"","id":"12569"},{"score":"","id":"12532"},{"score":"","id":"11584"},{"score":"","id":"9683"},{"score":"","id":"12317"},{"score":"","id":"12393"},{"score":"","id":"11916"},{"score":"","id":"10303"},{"score":"","id":"4891"},{"score":"","id":"0524"},{"score":"","id":"2842"},{"score":"","id":"12210"},{"score":"","id":"8416"},{"score":"","id":"9525"},{"score":"","id":"12263"},{"score":"","id":"10872"},{"score":"","id":"10516"},{"score":"","id":"12446"},{"score":"","id":"11199"},{"score":"","id":"11953"},{"score":"","id":"8358"},{"score":"","id":"8117"},{"score":"","id":"12524"},{"score":"","id":"11670"},{"score":"","id":"7422"},{"score":"","id":"12390"},{"score":"","id":"11982"},{"score":"","id":"4923"},{"score":"","id":"9992"},{"score":"","id":"10698"},{"score":"","id":"9383"},{"score":"","id":"12458"},{"score":"","id":"7653"},{"score":"","id":"11842"},{"score":"","id":"12098"},{"score":"","id":"11746"},{"score":"","id":"10987"},{"score":"","id":"11229"},{"score":"","id":"12429"},{"score":"7.6","id":"11747"},{"score":"","id":"12177"},{"score":"","id":"11581"},{"score":"","id":"7839"},{"score":"","id":"12439"},{"score":"","id":"8322"},{"score":"","id":"12482"},{"score":"2.4","id":"11342"},{"score":"","id":"11662"},{"score":"","id":"11658"},{"score":"","id":"11510"},{"score":"","id":"11627"},{"score":"","id":"9854"},{"score":"","id":"11886"},{"score":"","id":"8268"},{"score":"","id":"12459"},{"score":"","id":"12160"},{"score":"","id":"12430"},{"score":"3.9","id":"11185"},{"score":"","id":"12206"},{"score":"1.0","id":"11254"},{"score":"","id":"9927"},{"score":"","id":"11600"},{"score":"","id":"12395"},{"score":"","id":"10298"},{"score":"","id":"11211"},{"score":"","id":"12392"},{"score":"","id":"12391"},{"score":"","id":"11381"},{"score":"","id":"11890"},{"score":"","id":"11231"},{"score":"","id":"10703"},{"score":"","id":"11963"},{"score":"","id":"11979"},{"score":"","id":"12140"},{"score":"","id":"6997"},{"score":"","id":"11202"},{"score":"","id":"9693"},{"score":"","id":"11228"},{"score":"","id":"12202"},{"score":"","id":"12512"},{"score":"","id":"11874"},{"score":"","id":"10734"},{"score":"","id":"10720"},{"score":"","id":"11526"},{"score":"","id":"12460"},{"score":"","id":"10391"},{"score":"","id":"12153"},{"score":"","id":"10110"},{"score":"","id":"12264"},{"score":"","id":"10868"}]},"version":"1.0","encoding":"ISO-8859-1"}